{
   "AboutUsUrl" : "http://www.mobile-knowledge.com",
   "AccountActivationDisabled" : "false",
   "Admin.CompanySettings": "ShowEstimateWarning,DestinationIsRequired,HideDestination,DisabledTutorialSlides,IBS.TimeDifference,IBS.PickupZoneToExclude,IBS.DestinationZoneToExclude,IBS.ValidateDestinationZone,IBS.ValidatePickupZone,HideCallDispatchButton,DefaultBookingSettings.ChargeTypeId,DefaultBookingSettings.NbPassenger,DefaultBookingSettings.ProviderId,DefaultBookingSettings.VehicleTypeId,Receipt.Note,HideReportProblem,OrderStatus.ServerPollingInterval,IBS.NoteTemplate,AccountActivationDisabled,AvailableVehicles.Enabled,AvailableVehicles.Radius,AvailableVehicles.Count,Store.AppleLink,Store.PlayLink",
   "APNS.CertificatePassword": "TaxiHail",
   "APNS.ProductionCertificatePath": "../../Certificates/production.p12",
   "APNS.DevelopmentCertificatePath": "../../Certificates/development.p12",
   "CreditCardIsMandatory" : "true",
   "DefaultPhoneNumber" : "18666245330",
   "DefaultPhoneNumberDisplay" : "1.866.624.5330",
   "Direction.FlateRate" : "3.45",
   "Direction.RatePerKm" : "1.70",
   "GCM.PackageName": "com.apcurium.MK.TaxiHailDemo",
   "Receipt.Note": "Thank You!<br>The Taxi Hail Team",
   "TaxiHail.ApplicationKey" : "TaxiHail",
   "TaxiHail.AccentColor" : "#0057a3",
   "TaxiHail.EmailFontColor" : "#000",
   "TaxiHail.SiteName" : "Dev",
   "IBS.WebServicesUrl" : "http://apcuriumibs:6928/XDS_IASPI.DLL/soap/",
   "IBS.WebServicesPassword" : "test",   
   "IBS.WebServicesUserName" : "taxi", 
   "GeoLoc.DefaultLatitude" : "45.516667",
   "GeoLoc.DefaultLongitude" : "-73.65",
   "GeoLoc.SearchFilter" : "{0},ottawa,on,canada&region=ca",
   "GoogleMapKey": "AIzaSyAd-ezA2SeVTSNqsu6aMmAkdlP3UqEVPWE",
   "LowerLeftLatitude" : "0",
   "LowerLeftLongitude" : "0",
   "Map.PlacesApiKey" : "AIzaSyAAgAGS4SjtSwqni_wpgCo2XnY30m0rhLs",
   "NumberOfCharInRefineAddress" : "10",
   "PriceFormat" : "en-US",   
   "PushNotificationsEnabled" : "true",
   "SendReceiptAvailable" : "true",
   "ShowEstimate" : "true",   
   "Smtp.Credentials.Password" : "Password01",
   "Smtp.Credentials.Username" : "TaxiHail",
   "StreetNumberScreenEnabled" : "true",   
   "UpperRightLatitude" : "0",
   "UpperRightLongitude" : "0",
   "VehicleTypeSelectionEnabled" : "true",
}
